{
  "schemaVersion": 1,
  "id": "neverket-minimap",
  "version": "${version}",
  "name": "Neverket Minimap",
  "description": "A minimap whose explored terrain is assembled from vanilla maps collected by the player.",
  "authors": ["Neverket Minimap contributors"],
  "license": "MIT",
  "environment": "client",
  "entrypoints": {
    "client": [
      "dev.cartographer.minimap.CartographerMinimapClient"
    ]
  },
  "depends": {
    "fabricloader": ">=0.19.3",
    "minecraft": "~26.2",
    "java": ">=25",
    "fabric-api": ">=0.154.2"
  }
}
